firstbatch/.DS_Store
firstbatch/__init__.py
firstbatch/algorithm/__init__.py
firstbatch/algorithm/base.py
firstbatch/algorithm/blueprint/__init__.py
firstbatch/algorithm/blueprint/base.py
firstbatch/algorithm/blueprint/library.py
firstbatch/algorithm/custom.py
firstbatch/algorithm/factory.py
firstbatch/algorithm/registry.py
firstbatch/algorithm/simple.py
firstbatch/async_core.py
firstbatch/client/__init__.py
firstbatch/client/async_client.py
firstbatch/client/base.py
firstbatch/client/schema.py
firstbatch/client/sync.py
firstbatch/client/wrapper.py
firstbatch/constants.py
firstbatch/core.py
firstbatch/imports/__init__.py
firstbatch/logger_conf.py
firstbatch/lossy/__init__.py
firstbatch/lossy/base.py
firstbatch/lossy/product.py
firstbatch/lossy/scalar.py
firstbatch/utils.py
firstbatch/vector_store/__init__.py
firstbatch/vector_store/base.py
firstbatch/vector_store/chroma.py
firstbatch/vector_store/pinecone.py
firstbatch/vector_store/qdrant.py
firstbatch/vector_store/schema.py
firstbatch/vector_store/supabase.py
firstbatch/vector_store/typesense.py
firstbatch/vector_store/utils.py
firstbatch/vector_store/weaviate.py
firstbatch-0.1.73.dist-info/LICENSE
firstbatch-0.1.73.dist-info/METADATA
firstbatch-0.1.73.dist-info/WHEEL
firstbatch-0.1.73.dist-info/RECORD
