Metadata-Version: 2.1
Name: firstbatch
Version: 0.1.73
Summary: FirstBatch SDK for integrating user embeddings to your project. Add real-time personalization to your AI application without user data.
License: MIT
Author: andthattoo
Author-email: omer@firstbatch.xyz
Requires-Python: >=3.9,<3.13
Classifier: License :: OSI Approved :: MIT License
Classifier: Programming Language :: Python :: 3
Classifier: Programming Language :: Python :: 3.9
Classifier: Programming Language :: Python :: 3.10
Classifier: Programming Language :: Python :: 3.11
Provides-Extra: chromadb
Provides-Extra: pinecone
Provides-Extra: product
Provides-Extra: supabase
Provides-Extra: typesense
Provides-Extra: weaviate
Requires-Dist: chromadb (>=0.4.13,<0.5.0) ; extra == "chromadb"
Requires-Dist: dataclasses-json (>=0.6.1,<0.7.0)
Requires-Dist: httpx (>=0.25.0,<0.26.0)
Requires-Dist: nanopq (>=0.2.0,<0.3.0) ; extra == "product"
Requires-Dist: numpy (>=1.26.0,<2.0.0)
Requires-Dist: pinecone-client (>=2.2.4,<3.0.0) ; extra == "pinecone"
Requires-Dist: pydantic (==1.10.13)
Requires-Dist: requests (>=2.31.0,<3.0.0)
Requires-Dist: tdigest (>=0.5.2.2,<0.6.0.0)
Requires-Dist: typesense (>=0.17.0,<0.18.0) ; extra == "typesense"
Requires-Dist: vecs (>=0.4.1,<0.5.0) ; extra == "supabase"
Requires-Dist: weaviate-client (>=3.24.2,<4.0.0) ; extra == "weaviate"
